ExampleClient.py
ExampleServer.py
PySocketLib/__init__.py
PySocketLib/CExceptions/InitExceptions.py
PySocketLib/CExceptions/ProtocolExceptions.py
PySocketLib/CExceptions/RunTime.py
PySocketLib/CExceptions/__init__.py
PySocketLib/Client/Client.py
PySocketLib/Client/ConnectedClient.py
PySocketLib/Client/TCPClient.py
PySocketLib/Client/UDPClient.py
PySocketLib/Client/__init__.py
PySocketLib/Server/Server.py
PySocketLib/Server/TCPServer.py
PySocketLib/Server/UDPServer.py
PySocketLib/Server/__init__.py
PySocketLib/Utility/__init__.py
PySocketLib/Utility/Protocol/Protocol.py
PySocketLib/Utility/Protocol/__init__.py
PySocketLib-0.3.2.dist-info/LICENSE
PySocketLib-0.3.2.dist-info/METADATA
PySocketLib-0.3.2.dist-info/WHEEL
PySocketLib-0.3.2.dist-info/top_level.txt
PySocketLib-0.3.2.dist-info/RECORD
