Metadata-Version: 2.1
Name: PySocketLib
Version: 0.3.2
Summary: Library to simplify working with socket
Author-email: Samsonov Igor <ig.samsonov10@yandex.ru>
Project-URL: Homepage, https://github.com/Minuta18/PySocketLib
Project-URL: Bug Tracker, https://github.com/Minuta18/PySocketLib/issues
Classifier: Programming Language :: Python :: 3
Classifier: License :: OSI Approved :: MIT License
Classifier: Operating System :: OS Independent
Requires-Python: >=3.7
License-File: LICENSE
